setup.py
gitlab/__init__.py
gitlab/exceptions.py
gitlab_tests/__init__.py
gitlab_tests/pyapi-gitlab_test.py
pyapi_gitlab.egg-info/PKG-INFO
pyapi_gitlab.egg-info/SOURCES.txt
pyapi_gitlab.egg-info/dependency_links.txt
pyapi_gitlab.egg-info/pbr.json
pyapi_gitlab.egg-info/requires.txt
pyapi_gitlab.egg-info/top_level.txt