Metadata-Version: 1.0
Name: pyapi-gitlab
Version: 7.5.3
Summary: Gitlab API wrapper for Gitlab 7.X
Home-page: http://github.com/itxaka/pyapi-gitlab/
Author: Itxaka Serrano Garcia
Author-email: itxakaserrano@gmail.com
License: GPL3
Keywords: gitlab git wrapper
Platform: UNKNOWN
